README.md
setup.cfg
setup.py
bin/FIT3D_output_rss_seg2cube.py
bin/ana_single.py
bin/ana_single_kin.py
bin/ana_spec.py
bin/auto_ssp.py
bin/auto_ssp_elines_rnd.py
bin/auto_ssp_elines_rnd_NR.py
bin/auto_ssp_elines_rnd_rss.py
bin/auto_ssp_elines_rnd_rss_disp_min.py
bin/auto_ssp_elines_rnd_rss_sigma_inst.py
bin/auto_ssp_elines_rnd_rss_sigma_inst_disp_min.py
bin/auto_ssp_elines_rnd_rss_sigma_inst_guided.py
bin/auto_ssp_elines_rnd_sigma_inst.py
bin/auto_ssp_elines_rnd_sigma_inst_NR.py
bin/auto_ssp_elines_rnd_sigma_inst_evar.py
bin/auto_ssp_elines_rnd_sigma_inst_sigma_rnd.py
bin/auto_ssp_elines_single.py
bin/auto_ssp_elines_single_sigma_inst.py
bin/auto_ssp_errcol_sigma.py
bin/auto_ssp_sigma_inst.py
bin/auto_ssp_sigma_inst_evar.py
bin/call_cmnd.py
bin/clean_Ha_map.py
bin/clean_cubes_map.py
bin/clean_nan.py
bin/cont_seg_all.py
bin/cont_seg_all_SN.py
bin/correct_vel_map_cube_rot.py
bin/create_mask_map.py
bin/csv_to_map.seg.py
bin/detect_peaks.py
bin/fit_elines.py
bin/fit_elines_LM.py
bin/fit_elines_rnd.py
bin/flux_elines_cube_EW.py
bin/get_CS_slice.py
bin/get_Ha.py
bin/get_SN_cube.py
bin/get_SN_rss.py
bin/get_index_output_auto_ssp_elines_rnd_rss_outFIT3D.py
bin/get_slice.py
bin/imarith.py
bin/img2spec_e.py
bin/index_seg_cube.py
bin/kin_cube_elines.py
bin/kin_cube_elines_LM.py
bin/kin_cube_elines_rnd.py
bin/kin_rss_elines.py
bin/kin_rss_elines_LM.py
bin/kin_rss_elines_rnd.py
bin/map_auto_ssp_AGE_MET_rnd.seg.py
bin/map_auto_ssp_rnd.seg.py
bin/med2df.py
bin/pack_NAME.py
bin/pack_results_name.py
bin/plot_ana_spec_resume.py
bin/radial_sum_cube_e.py
bin/read_img_header.py
bin/redshift_config.py
bin/rss_seg2cube.py
bin/smooth_spec_clip_cube.py
bin/spec_extract_cube.py
bin/spec_extract_cube_error.py
bin/spec_extract_cube_mean.py
bin/spec_extract_diffuse.py
bin/sum_mass_age.py
bin/vel_eline_cube.py
bin/vel_eline_spec.py
bin/write_img_header.py
pyFIT3D/__init__.py
pyFIT3D/common/__init__.py
pyFIT3D/common/auto_ssp_tools.py
pyFIT3D/common/constants.py
pyFIT3D/common/gas_tools.py
pyPipe3D.egg-info/PKG-INFO
pyPipe3D.egg-info/SOURCES.txt
pyPipe3D.egg-info/dependency_links.txt
pyPipe3D.egg-info/not-zip-safe
pyPipe3D.egg-info/requires.txt
pyPipe3D.egg-info/top_level.txt