Metadata-Version: 1.1
Name: pyPipe3D
Version: 1.1.5
Summary: A Python implementation of the FIT3D code
Home-page: https://gitlab.com/pipe3d/pyPipe3D
Author: pipe3d
Author-email: pipe3d@astro.unam.mx
License: MIT
Download-URL: https://gitlab.com/pipe3d/pyPipe3D/-/archive/v1.1.5/pyPipe3D-v1.1.5.tar.gz
Keywords: galaxies
Platform: UNKNOWN
Classifier: Development Status :: 5 - Production/Stable
Classifier: License :: OSI Approved :: MIT License
Classifier: Programming Language :: Python :: 3.7
Classifier: Topic :: Scientific/Engineering :: Astronomy
